[{"datasetid": "food-vendors", "recordid": "e1c4dceb7fc7a2871cb8be38f33e5d1c71341229", "fields": {"status": "open", "description": "Hot Dogs", "geo_localarea": "Downtown", "geom": {"type": "Point", "coordinates": [-123.114069374134, 49.277427325294]}, "location": "East Side of 800 Beatty St - 6 Metres South of Robson St", "key": "DT48", "vendor_type": "vendor_food"}, "record_timestamp": "2019-06-03T04:01:35.843-07:00"},{"datasetid": "food-vendors", "recordid": "3178d2805a2c2ac958170361f0517a7bada3e983", "fields": {"status": "open", "description": "Hot Dogs", "geo_localarea": "West End", "geom": {"type": "Point", "coordinates": [-123.142926123068, 49.28449251733]}, "location": "South Side of 1700 Beach Ave - East Side of Bidwell St", "key": "EB04", "vendor_type": "vendor_food"}, "record_timestamp": "2019-06-03T04:01:35.843-07:00"},{"datasetid": "food-vendors", "recordid": "258b731cf6b85b4bc2a437e2362ac920e835b88f", "fields": {"status": "open", "description": "Hot Dogs", "geo_localarea": "Downtown", "geom": {"type": "Point", "coordinates": [-123.122779848109, 49.2747502295582]}, "location": "South Side of 300 Davie St - 6 Metres East of Hamilton St", "key": "DT21", "vendor_type": "vendor_food"}, "record_timestamp": "2019-06-03T04:01:35.843-07:00"},{"datasetid": "food-vendors", "recordid": "ac29f2b3f90f0ac1523675688944e5ab092a9af7", "fields": {"status": "open", "description": "Hot Dogs", "geo_localarea": "Kensington-Cedar Cottage", "geom": {"type": "Point", "coordinates": [-123.069072741187, 49.2622160476583]}, "location": "South Side of 1700 East Broadway - 37 Metres East of Commercial Dr", "key": "OD05", "vendor_type": "vendor_food"}, "record_timestamp": "2019-06-03T04:01:35.843-07:00"},{"datasetid": "food-vendors", "recordid": "c76e96bbebe1fe6d8c562efbe918cd12acd4cc4e", "fields": {"status": "open", "description": "Hot Dogs", "geo_localarea": "Downtown", "geom": {"type": "Point", "coordinates": [-123.108008079327, 49.2787930537543]}, "location": "Expo Boulevard - 20 Metres West of Abbott St", "key": "DT10", "vendor_type": "vendor_food"}, "record_timestamp": "2019-06-03T04:01:35.843-07:00"},{"datasetid": "food-vendors", "recordid": "507a433103623ec9d2dbf0cc7bc3a1730cc667c4", "fields": {"status": "open", "description": "Japanese Cuisine", "geo_localarea": "Downtown", "geom": {"type": "Point", "coordinates": [-123.116782, 49.286949]}, "location": "South Side of 900 W Hastings - 10 metres East of Burrard St", "key": "DT61", "business_name": "Actual Oden", "vendor_type": "vendor_food"}, "record_timestamp": "2019-06-03T04:01:35.843-07:00"},{"datasetid": "food-vendors", "recordid": "1d0111185468ed1ecea758438dd2163c6cb0f68e", "fields": {"status": "open", "description": "Mexican Cuisine", "geo_localarea": "Downtown", "geom": {"type": "Point", "coordinates": [-123.113567537336, 49.2865282200574]}, "location": "North Side of 700 W Cordova St - 14 metres East of Howe St", "key": "DT57", "business_name": "Arturo's Mexico To Go", "vendor_type": "vendor_food"}, "record_timestamp": "2019-06-03T04:01:35.843-07:00"},{"datasetid": "food-vendors", "recordid": "587220b5a5500c9102dbf47ad8c80500f59441f0", "fields": {"status": "open", "description": "Australian Pies", "geo_localarea": "Downtown", "geom": {"type": "Point", "coordinates": [-123.118192426382, 49.2869519782249]}, "location": "Authorised Parking Meter - 1000 W Pender St", "key": "C18", "business_name": "Aussie Pie Guy", "vendor_type": "vendor_food"}, "record_timestamp": "2019-06-03T04:01:35.843-07:00"},{"datasetid": "food-vendors", "recordid": "e833039d7b1f4f7c5e1fd5d739128cdaf9299732", "fields": {"status": "open", "description": "Kebabs", "geo_localarea": "Downtown", "geom": {"type": "Point", "coordinates": [-123.12034, 49.281785]}, "location": "North Side of 700 Robson St - 50 Metres West of Granville St", "key": "DT40", "business_name": "Cazba Express", "vendor_type": "vendor_food"}, "record_timestamp": "2019-06-03T04:01:35.843-07:00"},{"datasetid": "food-vendors", "recordid": "a9bfbc32bb91a34d7d267d59f274ba24707a6022", "fields": {"status": "open", "description": "Vegetarian", "geo_localarea": "Downtown", "geom": {"type": "Point", "coordinates": [-123.115773447168, 49.287612530414]}, "location": "Authorised Parking Meter - North Side of W Cordova St", "key": "C12", "business_name": "Chickpea", "vendor_type": "vendor_food"}, "record_timestamp": "2019-06-03T04:01:35.843-07:00"},{"datasetid": "food-vendors", "recordid": "a3c89055360db4847bce26e738f6d506783b295c", "fields": {"status": "open", "description": "French Crepes", "geo_localarea": "Downtown", "geom": {"type": "Point", "coordinates": [-123.106627254804, 49.2839897490076]}, "location": "North Side of 100 Water St - 10 Metres West of Abbott St", "key": "GT02", "business_name": "Chou Chou Crepes", "vendor_type": "vendor_food"}, "record_timestamp": "2019-06-03T04:01:35.843-07:00"},{"datasetid": "food-vendors", "recordid": "a34545a57a8705b11aa60c2651c8fd6309f829b1", "fields": {"status": "open", "description": "Venezuelan Cuisine", "geo_localarea": "Downtown", "geom": {"type": "Point", "coordinates": [-123.119288, 49.287838]}, "location": "Authorised Parking Meter - 1000 W Hastings St", "key": "C21", "business_name": "Come Arepa", "vendor_type": "vendor_food"}, "record_timestamp": "2019-06-03T04:01:35.843-07:00"},{"datasetid": "food-vendors", "recordid": "be25db56426c1c8f1dc5ade83b99108d4c85da83", "fields": {"status": "open", "description": "Greek Cuisine", "geo_localarea": "West End", "geom": {"type": "Point", "coordinates": [-123.135271203846, 49.2912416908619]}, "location": "South Side of 1700 Robson St - 10 Metres East of Denman St", "key": "DT71", "business_name": "Didi's Greek", "vendor_type": "vendor_food"}, "record_timestamp": "2019-06-03T04:01:35.843-07:00"},{"datasetid": "food-vendors", "recordid": "45a0ac617e112a35da54d8d46d357c25331c2523", "fields": {"status": "open", "description": "Wraps and Sandwiches", "geo_localarea": "Downtown", "geom": {"type": "Point", "coordinates": [-123.121388, 49.282313]}, "location": "South Side of 800 Robson St - 28 Metres East of Hornby St", "key": "DT75", "business_name": "Eat Chicken Wraps", "vendor_type": "vendor_food"}, "record_timestamp": "2019-06-03T04:01:35.843-07:00"},{"datasetid": "food-vendors", "recordid": "b23cf35391d3adf3cbe92c1c35739fee6a91d72e", "fields": {"status": "open", "description": "Comfort Food", "geo_localarea": "Downtown", "geom": {"type": "Point", "coordinates": [-123.124511374389, 49.2820545294215]}, "location": "Authorised Parking Meter East Side of 900 Burrard St", "key": "C8", "business_name": "Gourmet Syndicate", "vendor_type": "vendor_food"}, "record_timestamp": "2019-06-03T04:01:35.843-07:00"},{"datasetid": "food-vendors", "recordid": "391c9469da20a59570f96851cd404addc1bd0132", "fields": {"status": "open", "description": "Hot Dogs", "geo_localarea": "Downtown", "geom": {"type": "Point", "coordinates": [-123.117884, 49.286363]}, "location": "East Side of 500 Burrard St - 6 Metres South of West Pender St", "key": "DT26", "business_name": "Japadog", "vendor_type": "vendor_food"}, "record_timestamp": "2019-06-03T04:01:35.843-07:00"},{"datasetid": "food-vendors", "recordid": "4e55acda15a5cdfcd85733ad6f31c61fe88283ac", "fields": {"status": "open", "description": "Chinese Cuisine", "geo_localarea": "West End", "geom": {"type": "Point", "coordinates": [-123.12561890857, 49.2865915482477]}, "location": "Authorised Parking Meter North Side of Alberni St - East of Bute St", "key": "C17", "business_name": "Le Tigre", "vendor_type": "vendor_food"}, "record_timestamp": "2019-06-03T04:01:35.843-07:00"},{"datasetid": "food-vendors", "recordid": "1c9881a79e38a4a5bd6ef949262ca6595a282b1b", "fields": {"status": "open", "description": "Hot Dogs", "geo_localarea": "West End", "geom": {"type": "Point", "coordinates": [-123.142526485066, 49.2875878236052]}, "location": "South Side of 1800 Beach Av - West of Davie St", "key": "EB07", "business_name": "Mac BBQ", "vendor_type": "vendor_food"}, "record_timestamp": "2019-06-03T04:01:35.843-07:00"},{"datasetid": "food-vendors", "recordid": "184f4fe07daac88c718d195e5d47a1b2cc11ef84", "fields": {"status": "open", "description": "Japanese Cuisine", "geo_localarea": "Downtown", "geom": {"type": "Point", "coordinates": [-123.117633, 49.284218]}, "location": "West Side of Howe St - South of Dunsmuir St", "key": "DT16", "business_name": "Mogu", "vendor_type": "vendor_food"}, "record_timestamp": "2019-06-03T04:01:35.843-07:00"},{"datasetid": "food-vendors", "recordid": "a2cadaa489bee60e0976de3f266d2856045547a5", "fields": {"status": "open", "description": "Italian Cuisine", "geo_localarea": "Downtown", "geom": {"type": "Point", "coordinates": [-123.119039, 49.281957]}, "location": "West Side of Granville St - 75 Metres North of Robson St", "key": "DT67", "business_name": "Mr. Arancino", "vendor_type": "vendor_food"}, "record_timestamp": "2019-06-03T04:01:35.843-07:00"},{"datasetid": "food-vendors", "recordid": "1cee0537ebe91ca445f2f93e4515ac17e4b2641f", "fields": {"status": "open", "description": "Sandwiches", "geo_localarea": "Downtown", "geom": {"type": "Point", "coordinates": [-123.118453808195, 49.2825423250662]}, "location": "South Side of 700 W Georgia St - 20 Metres West of Granville St", "key": "GM15", "business_name": "Mr. Sandwich", "vendor_type": "vendor_food"}, "record_timestamp": "2019-06-03T04:01:35.843-07:00"},{"datasetid": "food-vendors", "recordid": "6c8d9f4ff0711e0c675dae0c637fd3d04406d2dc", "fields": {"status": "open", "description": "Shawarma", "geo_localarea": "Downtown", "geom": {"type": "Point", "coordinates": [-123.12148094657, 49.2825844484842]}, "location": "North Side of 800 Robson St - East of Hornby St", "key": "DT58", "business_name": "Mr. Shawarma", "vendor_type": "vendor_food"}, "record_timestamp": "2019-06-03T04:01:35.843-07:00"},{"datasetid": "food-vendors", "recordid": "b3c00abb4cac6ed2bd0e766a7600a81213b16c10", "fields": {"status": "open", "description": "Potato Based Dishes", "geo_localarea": "West End", "geom": {"type": "Point", "coordinates": [-123.128965, 49.279378]}, "location": "West Side of 1100 Burrard St - 10 Metres North of Davie St", "key": "DT35", "business_name": "Russett Shack", "vendor_type": "vendor_food"}, "record_timestamp": "2019-06-03T04:01:35.843-07:00"},{"datasetid": "food-vendors", "recordid": "1f9efe7ed19061fa7aeb1675a0db0965937c8088", "fields": {"status": "open", "description": "Hot Dogs", "geo_localarea": "Downtown", "geom": {"type": "Point", "coordinates": [-123.123682322296, 49.2910821453032]}, "location": "Coal Harbour Seawall  - 200 Metres Northeast of Broughton St", "key": "DT56", "business_name": "Sea Dogs", "vendor_type": "vendor_food"}, "record_timestamp": "2019-06-03T04:01:35.843-07:00"},{"datasetid": "food-vendors", "recordid": "51d80f89142eb333a0416de90becac93a613a05b", "fields": {"status": "open", "description": "Hot Dogs", "geo_localarea": "Downtown", "geom": {"type": "Point", "coordinates": [-123.111358832752, 49.2851739115674]}, "location": "North Side of 500 W Cordova St - 59 Metres West of Richards St", "key": "DT32", "business_name": "Tandoori Tikka Dog", "vendor_type": "vendor_food"}, "record_timestamp": "2019-06-03T04:01:35.843-07:00"},{"datasetid": "food-vendors", "recordid": "dad304b6bbc7edfb016e8c4d7c28fac7ce425ebe", "fields": {"status": "open", "description": "Vegetarian and Vegan", "geo_localarea": "Downtown", "geom": {"type": "Point", "coordinates": [-123.121519625651, 49.2738358886872]}, "location": "East Side of 1200 Pacific Boulevard - 10 Metres South of Davie St", "key": "DT72", "business_name": "The Loving Hut", "vendor_type": "vendor_food"}, "record_timestamp": "2019-06-03T04:01:35.843-07:00"},{"datasetid": "food-vendors", "recordid": "bc09db96c9b10365a641e159db67b8d5c99c372d", "fields": {"status": "open", "description": "Hot Dogs", "geo_localarea": "Downtown", "geom": {"type": "Point", "coordinates": [-123.119509851201, 49.2728501609174]}, "location": "Foot of Davie St - 2 Metres South of Marinaside Cres.", "key": "DT47", "business_name": "V Dub Dogs", "vendor_type": "vendor_food"}, "record_timestamp": "2019-06-03T04:01:35.843-07:00"},{"datasetid": "food-vendors", "recordid": "7c4c95dd2d025e7fe7446de3623367650e4891bd", "fields": {"status": "open", "description": "Indian Cuisine", "geo_localarea": "Downtown", "geom": {"type": "Point", "coordinates": [-123.122541268298, 49.2854937288055]}, "location": "Authorised Parking Meter North Side of 1000 W Georgia St", "key": "C24", "business_name": "Vij's Railway Express", "vendor_type": "vendor_food"}, "record_timestamp": "2019-06-03T04:01:35.843-07:00"},{"datasetid": "food-vendors", "recordid": "22ab66184878554b6bf8b1e5abe6eabeab2c37e0", "fields": {"status": "open", "description": "Hot Dogs", "geo_localarea": "Downtown", "geom": {"type": "Point", "coordinates": [-123.114194279397, 49.2797972582368]}, "location": "South Side of 200 West Georgia St - 8 Metres East of Hamilton St", "key": "DT73", "business_name": "Tandoori Tikka Dog", "vendor_type": "vendor_food"}, "record_timestamp": "2019-06-03T04:01:35.843-07:00"},{"datasetid": "food-vendors", "recordid": "f4d9e6101a3946a33aa7cff4790ef1c695e0bd95", "fields": {"status": "open", "description": "Hot Dogs", "geo_localarea": "Downtown", "geom": {"type": "Point", "coordinates": [-123.122119558315, 49.2797455146803]}, "location": "East Side of 900 Granville St - 75 Metres South of Smithe St", "key": "GM11", "business_name": "Van Dog", "vendor_type": "vendor_food"}, "record_timestamp": "2019-06-03T04:01:35.843-07:00"},{"datasetid": "food-vendors", "recordid": "6f26ad5b414c01928feea72c6834eef98a4fce51", "fields": {"status": "open", "description": "Italian Cuisine", "geo_localarea": "Downtown", "geom": {"type": "Point", "coordinates": [-123.117533501725, 49.2869026428645]}, "location": "Authorised Parking Meter - West Side of 400 Burrard St", "key": "C1", "business_name": "Vie Niapolotan", "vendor_type": "vendor_food"}, "record_timestamp": "2019-06-03T04:01:35.843-07:00"},{"datasetid": "food-vendors", "recordid": "ae5a0b3f65b9559c277abc146e99e15ee55aa3d4", "fields": {"status": "open", "description": "Burgers and Fries", "geo_localarea": "Downtown", "geom": {"type": "Point", "coordinates": [-123.115175231669, 49.2845221170008]}, "location": "West Side of 500 Granville St - 10 Metres South of West Pender St", "key": "DT31", "business_name": "Yokabai", "vendor_type": "vendor_food"}, "record_timestamp": "2019-06-03T04:01:35.843-07:00"},{"datasetid": "food-vendors", "recordid": "7546af60a8a3746bdfbc9955d8a98c044f3fdf75", "fields": {"status": "open", "description": "Hot Dogs", "geo_localarea": "Downtown", "geom": {"type": "Point", "coordinates": [-123.120951896798, 49.2805178578306]}, "location": "East Side of 800 Granville St - 30 Metres North of Smithe St", "key": "GM05", "vendor_type": "vendor_food"}, "record_timestamp": "2019-06-03T04:01:35.843-07:00"},{"datasetid": "food-vendors", "recordid": "2c257843a2364445b02820195874e9d81e5148f2", "fields": {"status": "open", "description": "Hot Dogs", "geo_localarea": "Downtown", "geom": {"type": "Point", "coordinates": [-123.118426844134, 49.2824701485478]}, "location": "West Side of 700 Granville St - 5 Metres South of W Georgia St", "key": "GM18", "vendor_type": "vendor_food"}, "record_timestamp": "2019-06-03T04:01:35.843-07:00"},{"datasetid": "food-vendors", "recordid": "392fadf35c96817217dbf9f486a2b98b65a8fd4f", "fields": {"status": "open", "description": "Hot Dogs", "geo_localarea": "Downtown", "geom": {"type": "Point", "coordinates": [-123.119863220163, 49.2834680335098]}, "location": "South Side of 800 W Georgia St - 55 Metres West of Howe St", "key": "DT38", "vendor_type": "vendor_food"}, "record_timestamp": "2019-06-03T04:01:35.843-07:00"},{"datasetid": "food-vendors", "recordid": "ab98e9a898e0bad1e53580ce67b98c0b43ee7be8", "fields": {"status": "open", "description": "Hot Dogs", "geo_localarea": "Marpole", "geom": {"type": "Point", "coordinates": [-123.1170317349, 49.2098916792662]}, "location": "East Side of 8400 Cambie St - 75 Metres South of SW Marine Dr", "key": "OD12", "vendor_type": "vendor_food"}, "record_timestamp": "2019-06-03T04:01:35.843-07:00"},{"datasetid": "food-vendors", "recordid": "75454b1742ce12b5d739297ef9576a60f8cf4ab1", "fields": {"status": "open", "description": "Hot Dogs", "geo_localarea": "West End", "geom": {"type": "Point", "coordinates": [-123.123569702796, 49.2839220206803]}, "location": "North Side of 1000 Robson St", "key": "DT79", "business_name": "Ali's Hot Dogs", "vendor_type": "vendor_food"}, "record_timestamp": "2019-06-03T04:01:35.843-07:00"},{"datasetid": "food-vendors", "recordid": "9358f253c33f145accc6416db0232d306f85f3c0", "fields": {"status": "open", "description": "Dim Sum", "geo_localarea": "Downtown", "geom": {"type": "Point", "coordinates": [-123.112870852909, 49.2872354621354]}, "location": "East Side of 200 Howe St - 100 Metres North of W Cordova St", "key": "DT54", "business_name": "Dim Sum Express", "vendor_type": "vendor_food"}, "record_timestamp": "2019-06-03T04:01:35.843-07:00"},{"datasetid": "food-vendors", "recordid": "7e535bd3ea3053d01fb1c44088895b6d10132e9e", "fields": {"status": "open", "description": "Hot Dogs", "geo_localarea": "Mount Pleasant", "geom": {"type": "Point", "coordinates": [-123.101569148691, 49.2584746760419]}, "location": "West Side of 2900 Main St - 20 Metres North of E 14th Ave", "key": "OD18", "business_name": "Dog Meister", "vendor_type": "vendor_food"}, "record_timestamp": "2019-06-03T04:01:35.843-07:00"},{"datasetid": "food-vendors", "recordid": "c1651062d152f3cd76cd823903f2c7b7d6582584", "fields": {"status": "open", "description": "Local Meats and Seafood", "geo_localarea": "Downtown", "geom": {"type": "Point", "coordinates": [-123.118453, 49.288672]}, "location": "Authorised Parking Meter - Thurlow St at W Cordova St", "key": "C9", "business_name": "Feastro - The Rolling Bistro", "vendor_type": "vendor_food"}, "record_timestamp": "2019-06-03T04:01:35.843-07:00"},{"datasetid": "food-vendors", "recordid": "02870c5e792a9a80cdbc9df6b9f87b3a77c6c991", "fields": {"status": "open", "description": "Local Meats and Seafood", "geo_localarea": "Downtown", "geom": {"type": "Point", "coordinates": [-123.120345228347, 49.2824386635302]}, "location": "Authorised Parking Meter West Side of 700 Howe St", "key": "C16", "business_name": "Feastro The Rolling Bistro", "vendor_type": "vendor_food"}, "record_timestamp": "2019-06-03T04:01:35.843-07:00"},{"datasetid": "food-vendors", "recordid": "b6031a167f5836455f710fe123bc7ecd021765cd", "fields": {"status": "open", "description": "Hot Dogs", "geo_localarea": "West End", "geom": {"type": "Point", "coordinates": [-123.124363670916, 49.2824199268397]}, "location": "West Side of 800 Burrard St - 2.5 Metres North of Smithe St", "key": "DT52", "business_name": "Japadog", "vendor_type": "vendor_food"}, "record_timestamp": "2019-06-03T04:01:35.843-07:00"},{"datasetid": "food-vendors", "recordid": "3cead89964f85f6e0cd985cb26747f795416273e", "fields": {"status": "open", "description": "Lemonade and Crepes", "geo_localarea": "West End", "geom": {"type": "Point", "coordinates": [-123.144697763958, 49.2896827395781]}, "location": "South Side of 2000 Beach Av - 30 metres West of Chilco St", "key": "EB03", "business_name": "Lemon Sea", "vendor_type": "vendor_food"}, "record_timestamp": "2019-06-03T04:01:35.843-07:00"},{"datasetid": "food-vendors", "recordid": "af063764b120ced241b6340e18e416408aefc89b", "fields": {"status": "open", "description": "Kosher Israeli", "geo_localarea": "Downtown", "geom": {"type": "Point", "coordinates": [-123.11975, 49.285658]}, "location": "Authorised Parking Meter South Side of 1000 Dunsmuir St", "key": "C11", "business_name": "Meet to Eat", "vendor_type": "vendor_food"}, "record_timestamp": "2019-06-03T04:01:35.843-07:00"},{"datasetid": "food-vendors", "recordid": "8c310ee0f8bbf1766a84ae6de9878009dcedfd49", "fields": {"status": "open", "description": "Potato Based Dishes", "geo_localarea": "Downtown", "geom": {"type": "Point", "coordinates": [-123.120079603127, 49.2812971848513]}, "location": "West Side of 800 Granville St - 6 Metres South of Robson St", "key": "GM10", "business_name": "Potato Tornado", "vendor_type": "vendor_food"}, "record_timestamp": "2019-06-03T04:01:35.843-07:00"},{"datasetid": "food-vendors", "recordid": "e486bc33c477f88676556bfcf0c8897b93feddc6", "fields": {"status": "open", "description": "Asian Fusion", "geo_localarea": "Mount Pleasant", "geom": {"type": "Point", "coordinates": [-123.106548732322, 49.271307845851]}, "location": "Authorised Parking Meter East Side of 1600 Manitoba St", "key": "C25", "business_name": "Roaming Dragon", "vendor_type": "vendor_food"}, "record_timestamp": "2019-06-03T04:01:35.843-07:00"},{"datasetid": "food-vendors", "recordid": "edaaea2333ad31cec53a26b95ff67c349fdede65", "fields": {"status": "open", "description": "Indian Cuisine", "geo_localarea": "Downtown", "geom": {"type": "Point", "coordinates": [-123.11850128812, 49.2825721404215]}, "location": "South Side of 700 W Georgia St - 20 Metres West of Granville St", "key": "GM21", "business_name": "Soho Road Naan Kebab", "vendor_type": "vendor_food"}, "record_timestamp": "2019-06-03T04:01:35.843-07:00"},{"datasetid": "food-vendors", "recordid": "e03d4ec8986fb26585b708bea714fe7b4fa24fe4", "fields": {"status": "open", "description": "Thai Cuisine", "geo_localarea": "Downtown", "geom": {"type": "Point", "coordinates": [-123.122623764676, 49.2855321149763]}, "location": "Authorised Parking Meter North Side of 1000 W Georgia St", "key": "C26", "business_name": "Super Thai", "vendor_type": "vendor_food"}, "record_timestamp": "2019-06-03T04:01:35.843-07:00"},{"datasetid": "food-vendors", "recordid": "e720e4585e7f8ba6f01e488b31d842f90e280213", "fields": {"status": "open", "description": "Juice and Smoothies", "geo_localarea": "Downtown", "geom": {"type": "Point", "coordinates": [-123.12269699834, 49.2831023503318]}, "location": "South Side of 900 Robson - 6 Metres East of Burrard St", "key": "DT41", "business_name": "The Juice Truck", "vendor_type": "vendor_food"}, "record_timestamp": "2019-06-03T04:01:35.843-07:00"},{"datasetid": "food-vendors", "recordid": "d0227464ed43846d235a291314714edfad2934a8", "fields": {"status": "open", "description": "Juice and Smoothies", "geo_localarea": "Downtown", "geom": {"type": "Point", "coordinates": [-123.109452, 49.283032]}, "location": "Authorised Parking Meter West Side of 300 Cambie St", "key": "C6", "business_name": "The Juice Truck", "vendor_type": "vendor_food"}, "record_timestamp": "2019-06-03T04:01:35.843-07:00"},{"datasetid": "food-vendors", "recordid": "84c93f1a6bec41d7f68006a2c1bcbd9fd52142a1", "fields": {"status": "open", "description": "Sandwiches", "geo_localarea": "Downtown", "geom": {"type": "Point", "coordinates": [-123.122135785725, 49.2827533646573]}, "location": "South Side of 900 Robson St - 16 Metres West of Hornby St", "key": "DT42", "business_name": "Cheesey Does It", "vendor_type": "vendor_food"}, "record_timestamp": "2019-06-03T04:01:35.843-07:00"},{"datasetid": "food-vendors", "recordid": "542ae91f34dc2009de8cc8b55202f3faeb121834", "fields": {"status": "open", "description": "Drinks and Smoothies", "geo_localarea": "Downtown", "geom": {"type": "Point", "coordinates": [-123.115237361117, 49.2808012429435]}, "location": "North Side of W Georgia St - 10 Metres West of Homer St", "key": "DT05", "business_name": "Mr. Camaron", "vendor_type": "vendor_food"}, "record_timestamp": "2019-06-03T04:01:35.843-07:00"},{"datasetid": "food-vendors", "recordid": "0524364d16864287985c84480aac2ab82e67a939", "fields": {"status": "open", "description": "Middle Eastern Cuisine", "geo_localarea": "Downtown", "geom": {"type": "Point", "coordinates": [-123.11719039448, 49.2830199658932]}, "location": "East Side of 600 Granville St - 80 Metres North of W Georgia St", "key": "GM16", "business_name": "Mr. Shawarma", "vendor_type": "vendor_food"}, "record_timestamp": "2019-06-03T04:01:35.843-07:00"},{"datasetid": "food-vendors", "recordid": "c9c742923e54b44440ce592c2e8adf2a023fbea4", "fields": {"status": "open", "description": "Hot Dogs", "geo_localarea": "Downtown", "geom": {"type": "Point", "coordinates": [-123.112040050999, 49.2787463289182]}, "location": "East Side of 600 Beatty St - 6 Metres North of West Georgia St", "key": "DT01", "business_name": "Mr. Tube Steak", "vendor_type": "vendor_food"}, "record_timestamp": "2019-06-03T04:01:35.843-07:00"},{"datasetid": "food-vendors", "recordid": "0632db89aa6cf54175aed434d75891bf93ab9cd5", "fields": {"status": "open", "description": "Fruit Shakes, Smoothies and Juices", "geo_localarea": "West End", "geom": {"type": "Point", "coordinates": [-123.139739, 49.286003]}, "location": "Authorised Parking Meter North Side of 1600 Davie St", "key": "EB06", "business_name": "San Juan Family Farm", "vendor_type": "vendor_food"}, "record_timestamp": "2019-06-03T04:01:35.843-07:00"},{"datasetid": "food-vendors", "recordid": "bf74e234eec51434b748c2f732a6175bd20ac0f8", "fields": {"status": "open", "description": "Tacos and Burritos", "geo_localarea": "Downtown", "geom": {"type": "Point", "coordinates": [-123.120529317155, 49.2823011792112]}, "location": "Authorised Parking Meter West Side of 700 Howe St", "key": "C5", "business_name": "Tacofino", "vendor_type": "vendor_food"}, "record_timestamp": "2019-06-03T04:01:35.843-07:00"},{"datasetid": "food-vendors", "recordid": "6ee4bbb5b258d981f017c2d1c9c6d831531a35db", "fields": {"status": "open", "description": "Hot Dogs", "geo_localarea": "West End", "geom": {"type": "Point", "coordinates": [-123.143229444439, 49.2887284881581]}, "location": "South Side of 1900 Beach Ave - 17 Metres West of Gilford St", "key": "EB05", "vendor_type": "vendor_food"}, "record_timestamp": "2019-06-03T04:01:35.843-07:00"},{"datasetid": "food-vendors", "recordid": "5938063098f6f4decd68980faf54275a8447e3e6", "fields": {"status": "open", "description": "Hot Dogs", "geo_localarea": "Downtown", "geom": {"type": "Point", "coordinates": [-123.118235028068, 49.282319592487]}, "location": "East side of 700 Granville St - 6 Metres South W Georgia St", "key": "GM03", "vendor_type": "vendor_food"}, "record_timestamp": "2019-06-03T04:01:35.843-07:00"},{"datasetid": "food-vendors", "recordid": "75fc7db2071ba1b908b9ede4f7d316851bd3ada4", "fields": {"status": "open", "description": "Hot Dogs", "geo_localarea": "Downtown", "geom": {"type": "Point", "coordinates": [-123.106609298224, 49.2839891744052]}, "location": "North Side of 100 Water St - 10 Metres West of Abbott St", "key": "GT04", "vendor_type": "vendor_food"}, "record_timestamp": "2019-06-03T04:01:35.843-07:00"},{"datasetid": "food-vendors", "recordid": "9e089647d589226db1520fd3dbeb492f1c2c1d9c", "fields": {"status": "open", "description": "Hot Dogs", "geo_localarea": "Downtown", "geom": {"type": "Point", "coordinates": [-123.109160409686, 49.2844467906592]}, "location": "North Side of 300 Water St - 17 Metres West of Cambie St", "key": "GT05", "vendor_type": "vendor_food"}, "record_timestamp": "2019-06-03T04:01:35.843-07:00"},{"datasetid": "food-vendors", "recordid": "15b05b9d3ad7185b06224bd5b827aedffdf3a91a", "fields": {"status": "open", "description": "Hot Dogs", "geo_localarea": "Downtown", "geom": {"type": "Point", "coordinates": [-123.110258929798, 49.2798897004659]}, "location": "North Side of Dunsmuir St - 6 Metres East of Beatty St", "key": "DT02", "vendor_type": "vendor_food"}, "record_timestamp": "2019-06-03T04:01:35.843-07:00"},{"datasetid": "food-vendors", "recordid": "230a0feb775b6ef8345b14474fd4d85cf99d4c3b", "fields": {"status": "open", "description": "Hot Dogs", "geo_localarea": "West End", "geom": {"type": "Point", "coordinates": [-123.122731856953, 49.283488792081]}, "location": "West Side of 700 Burrard St - 15 Metres North of Robson St", "key": "DT37", "vendor_type": "vendor_food"}, "record_timestamp": "2019-06-03T04:01:35.843-07:00"},{"datasetid": "food-vendors", "recordid": "2f239b95bb5418b82435cd91d77d90e6cf2a0ac5", "fields": {"status": "open", "description": "Hot Dogs", "geo_localarea": "Downtown", "geom": {"type": "Point", "coordinates": [-123.122520505306, 49.2832224976244]}, "location": "North Side of 900 Robson St - 6 Metres East of Burrard St", "key": "DT13", "vendor_type": "vendor_food"}, "record_timestamp": "2019-06-03T04:01:35.843-07:00"},{"datasetid": "food-vendors", "recordid": "cea1461b253587ad83d0357ec6fa6a2c4c701361", "fields": {"status": "open", "description": "Seafood and Western", "geo_localarea": "Downtown", "geom": {"type": "Point", "coordinates": [-123.118591524118, 49.2823626147279]}, "location": "West Side of 700 Granville St - South of W Georgia St", "key": "GM13", "business_name": "BBKB Kaboom Box", "vendor_type": "vendor_food"}, "record_timestamp": "2019-06-03T04:01:35.843-07:00"},{"datasetid": "food-vendors", "recordid": "0e874e801897e929ce395aa05c6e93818744a4df", "fields": {"status": "open", "description": "Vegan Cuisine", "geo_localarea": "Downtown", "geom": {"type": "Point", "coordinates": [-123.122093113148, 49.2851936823208]}, "location": "Authorised Parking Meter - North Side of 1000 W Georgia St", "key": "C15", "business_name": "Bandidas", "vendor_type": "vendor_food"}, "record_timestamp": "2019-06-03T04:01:35.843-07:00"},{"datasetid": "food-vendors", "recordid": "3221356d9f13cf1c6cf7a1447148e9d2c6fbca6c", "fields": {"status": "open", "description": "Brasilian Cuisine", "geo_localarea": "Downtown", "geom": {"type": "Point", "coordinates": [-123.11684601808, 49.2819872240752]}, "location": "Authorised Parking Meter - East Side of 600 Seymour St", "key": "C14", "business_name": "Brasilian Roots", "vendor_type": "vendor_food"}, "record_timestamp": "2019-06-03T04:01:35.843-07:00"},{"datasetid": "food-vendors", "recordid": "50a0414989ec3378f49361005baa8b6efac2c652", "fields": {"status": "open", "description": "Variety Menu", "geo_localarea": "Downtown", "geom": {"type": "Point", "coordinates": [-123.121122, 49.282109]}, "location": "South Side of 800 Robson St- 13 Metres West of Howe St", "key": "DT74", "business_name": "Commissary Connect", "vendor_type": "vendor_food"}, "record_timestamp": "2019-06-03T04:01:35.843-07:00"},{"datasetid": "food-vendors", "recordid": "e2070018a0df7c9923533ef2bc081a4736befb26", "fields": {"status": "open", "description": "Variety Menu", "geo_localarea": "Downtown", "geom": {"type": "Point", "coordinates": [-123.118581094106, 49.2849051031527]}, "location": "West Side of 600 Hornby St - 6 Metres South of Dunsmuir St", "key": "DT70", "business_name": "Commissary Connect", "vendor_type": "vendor_food"}, "record_timestamp": "2019-06-03T04:01:35.843-07:00"},{"datasetid": "food-vendors", "recordid": "01911499ae013d006a96ee408af58892d55e528c", "fields": {"status": "open", "description": "Variety Menu", "geo_localarea": "Downtown", "geom": {"type": "Point", "coordinates": [-123.120309650843, 49.2835087650275]}, "location": "East Side of 700 Hornby St - 22 metres South of W Georgia St", "key": "DT59", "business_name": "Commissary Connect", "vendor_type": "vendor_food"}, "record_timestamp": "2019-06-03T04:01:35.843-07:00"},{"datasetid": "food-vendors", "recordid": "24ec834c8250be985ee06a37ca51825ee8118608", "fields": {"status": "open", "description": "Chowders and Soups", "geo_localarea": "Downtown", "geom": {"type": "Point", "coordinates": [-123.11746613169, 49.2828190132516]}, "location": "East Side of 600 Granville St - 30 Metres North of W Georgia St", "key": "GM20", "business_name": "Crab Park Chowdery", "vendor_type": "vendor_food"}, "record_timestamp": "2019-06-03T04:01:35.843-07:00"},{"datasetid": "food-vendors", "recordid": "e42964f64d19b6755133542744a65606100a384e", "fields": {"status": "open", "description": "Korean", "geo_localarea": "Downtown", "geom": {"type": "Point", "coordinates": [-123.12044362671, 49.2823678347768]}, "location": "Authorised Parking Meter West Side of 700 Howe St", "key": "C13", "business_name": "Disco Cheetah", "vendor_type": "vendor_food"}, "record_timestamp": "2019-06-03T04:01:35.843-07:00"},{"datasetid": "food-vendors", "recordid": "23cf72d1aebf020e8fe7ad20f125d3d096fa74d0", "fields": {"status": "open", "description": "Wraps and Sandwiches", "geo_localarea": "Downtown", "geom": {"type": "Point", "coordinates": [-123.12109855916, 49.2819285670653]}, "location": "West Side of 800 Howe St - 5 Metres South of Robson St", "key": "DT49", "business_name": "Eat Chicken Wraps", "vendor_type": "vendor_food"}, "record_timestamp": "2019-06-03T04:01:35.843-07:00"},{"datasetid": "food-vendors", "recordid": "9ebbdf6173e321b6f47ea2c2bbf7754d71093f95", "fields": {"status": "open", "description": "International Comfort Foods", "geo_localarea": "Downtown", "geom": {"type": "Point", "coordinates": [-123.114022, 49.286811]}, "location": "Authorised Parking Meter - North Side of 800 W Cordova St", "key": "C23", "business_name": "Fat Duck Mobile Eatery", "vendor_type": "vendor_food"}, "record_timestamp": "2019-06-03T04:01:35.843-07:00"},{"datasetid": "food-vendors", "recordid": "5c487572e8cd2b8e2fdb7d9a11dcb8c6e41f9f78", "fields": {"status": "open", "description": "Hot Dogs", "geo_localarea": "Fairview", "geom": {"type": "Point", "coordinates": [-123.138921554365, 49.2634838294021]}, "location": "South Side 1500 West Broadway - 6 Metres West of Granville St", "key": "OD03", "business_name": "Holy Smokes", "vendor_type": "vendor_food"}, "record_timestamp": "2019-06-03T04:01:35.843-07:00"},{"datasetid": "food-vendors", "recordid": "d1dd1b982ef238a58cf5e2505a79efab1110be4a", "fields": {"status": "open", "description": "Hot Dogs", "geo_localarea": "Downtown", "geom": {"type": "Point", "coordinates": [-123.112525974406, 49.2859060939777]}, "location": "North Side of 600 W Cordova St - 6 Metres East of Granville St", "key": "DT69", "business_name": "Japadog", "vendor_type": "vendor_food"}, "record_timestamp": "2019-06-03T04:01:35.843-07:00"},{"datasetid": "food-vendors", "recordid": "dc1f7505ed40f2a2c1a3c7033195a75ce6657f66", "fields": {"status": "open", "description": "Tacos and Fresh Salsas", "geo_localarea": "Kensington-Cedar Cottage", "geom": {"type": "Point", "coordinates": [-123.068886047286, 49.262216537032]}, "location": "South Side of 1700 E Broadway", "key": "OD06", "business_name": "La Bomba Taqueria", "vendor_type": "vendor_food"}, "record_timestamp": "2019-06-03T04:01:35.843-07:00"},{"datasetid": "food-vendors", "recordid": "fd0c566aac9b31997a0b8209de80ace53934bd8d", "fields": {"status": "open", "description": "Hot Dogs", "geo_localarea": "West End", "geom": {"type": "Point", "coordinates": [-123.14250504093, 49.287324013553]}, "location": "South Side of 1800 Beach Av - East of Davie St", "key": "EB01", "business_name": "Mac BBQ", "vendor_type": "vendor_food"}, "record_timestamp": "2019-06-03T04:01:35.843-07:00"},{"datasetid": "food-vendors", "recordid": "1793c3cb5015e45dbd0a367d61a5fba2eefe1347", "fields": {"status": "open", "description": "Middle Eastern Cuisine", "geo_localarea": "Downtown", "geom": {"type": "Point", "coordinates": [-123.119611425531, 49.2832896022047]}, "location": "South Side of 800 W Georgia St - 30 Metres West of Howe St", "key": "DT64", "business_name": "Marimba", "vendor_type": "vendor_food"}, "record_timestamp": "2019-06-03T04:01:35.843-07:00"},{"datasetid": "food-vendors", "recordid": "e224329707928f4edb14d7c186266efd8a67ee16", "fields": {"status": "open", "description": "Kebabs", "geo_localarea": "Downtown", "geom": {"type": "Point", "coordinates": [-123.115997593018, 49.283807299327]}, "location": "East Side of 500 Granville St - 10 Metres North of Dunsmuir St", "key": "GM17", "business_name": "Master Chef's Kebab House", "vendor_type": "vendor_food"}, "record_timestamp": "2019-06-03T04:01:35.843-07:00"},{"datasetid": "food-vendors", "recordid": "ba2e5e4dfa50cd4458532c7f4f648a5a156c3fe1", "fields": {"status": "open", "description": "Kosher Israeli", "geo_localarea": "West End", "geom": {"type": "Point", "coordinates": [-123.129163571627, 49.2792760359058]}, "location": "West Side of 1100 Burrard St - 10 Metres North of Davie St", "key": "DT15", "business_name": "Meet to Eat", "vendor_type": "vendor_food"}, "record_timestamp": "2019-06-03T04:01:35.843-07:00"},{"datasetid": "food-vendors", "recordid": "2704d7388dbe7ca56e7994369808abf92c4ef8a3", "fields": {"status": "open", "description": "Western", "geo_localarea": "Downtown", "geom": {"type": "Point", "coordinates": [-123.121307872222, 49.2822753151292]}, "location": "South Side of 800 Robson St  -30 Metres West of Howe St", "key": "DT39", "business_name": "Mo's Hot Dog Plus", "vendor_type": "vendor_food"}, "record_timestamp": "2019-06-03T04:01:35.843-07:00"},{"datasetid": "food-vendors", "recordid": "e442fb6f205c0c296ce6a418c6f8a2328635a5ef", "fields": {"status": "open", "description": "Shawarma", "geo_localarea": "Downtown", "geom": {"type": "Point", "coordinates": [-123.120163, 49.285361]}, "location": "Authorised Parking Meter - North Side of 1000 Melville St", "key": "C3", "business_name": "Mr. Shawarma", "vendor_type": "vendor_food"}, "record_timestamp": "2019-06-03T04:01:35.843-07:00"},{"datasetid": "food-vendors", "recordid": "445235d6cb1f02a26ab80c46cacebf0b554c1118", "fields": {"status": "open", "description": "Grilled Cheese and Soups", "geo_localarea": "Downtown", "geom": {"type": "Point", "coordinates": [-123.120684903216, 49.2822094865348]}, "location": "Authorised Parking Meter -West Side of 700 Howe St", "key": "C10", "business_name": "Mum's Grilled Cheese Truck", "vendor_type": "vendor_food"}, "record_timestamp": "2019-06-03T04:01:35.843-07:00"},{"datasetid": "food-vendors", "recordid": "909e836069b9b8f0ffa91833854073319a0fe384", "fields": {"status": "open", "description": "Asian Fusion", "geo_localarea": "Downtown", "geom": {"type": "Point", "coordinates": [-123.122918691376, 49.2830967068971]}, "location": "Authorised Parking Meter East Side of 800 Burrard St", "key": "C7", "business_name": "Roaming Dragon", "vendor_type": "vendor_food"}, "record_timestamp": "2019-06-03T04:01:35.843-07:00"},{"datasetid": "food-vendors", "recordid": "9ac74f3f900e7e7bd35056f9f79fd3e0d22388b4", "fields": {"status": "open", "description": "Thai Cuisine", "geo_localarea": "Downtown", "geom": {"type": "Point", "coordinates": [-123.121070522118, 49.2822804045159]}, "location": "North Side of 800 Robson St - 30 Metres West of Howe St", "key": "DT36", "business_name": "Suassy Thai", "vendor_type": "vendor_food"}, "record_timestamp": "2019-06-03T04:01:35.843-07:00"},{"datasetid": "food-vendors", "recordid": "0494eb52145e913c168ff0fd37ba9f1ea7cd8217", "fields": {"status": "open", "description": "Tacos and Burritos", "geo_localarea": "Downtown", "geom": {"type": "Point", "coordinates": [-123.119002, 49.286031]}, "location": "Authorised Parking Meter West Side 500 Burrard St", "key": "C4", "business_name": "Tacofino White Lightening", "vendor_type": "vendor_food"}, "record_timestamp": "2019-06-03T04:01:35.843-07:00"},{"datasetid": "food-vendors", "recordid": "f8f4506d812f7018c1b7732ff4142ca62c85b285", "fields": {"status": "open", "description": "Fried Chicken Sandwiches", "geo_localarea": "Downtown", "geom": {"type": "Point", "coordinates": [-123.118158491193, 49.2865384000861]}, "location": "Authorised Parking Meter West Side of 500 Burrard St", "key": "C20", "business_name": "The Fryinig Pan", "vendor_type": "vendor_food"}, "record_timestamp": "2019-06-03T04:01:35.843-07:00"},{"datasetid": "food-vendors", "recordid": "a283d770fec32bc37544036a171242ca0442f8f2", "fields": {"status": "open", "description": "Central European Desserts", "geo_localarea": "Downtown", "geom": {"type": "Point", "coordinates": [-123.119362, 49.287858]}, "location": "Authorised Parking Meter - 1000 W Hastings St", "key": "C22", "business_name": "The Praguery", "vendor_type": "vendor_food"}, "record_timestamp": "2019-06-03T04:01:35.843-07:00"},{"datasetid": "food-vendors", "recordid": "592f5635e68c953ff43bf74dae85a240ccb4ddee", "fields": {"status": "open", "description": "Caribbean", "geo_localarea": "Downtown", "geom": {"type": "Point", "coordinates": [-123.119509663147, 49.2880164317887]}, "location": "Authorised Parking Meter - East Side of Thurlow St - North of W Hastings St", "key": "C19", "business_name": "The Reef", "vendor_type": "vendor_food"}, "record_timestamp": "2019-06-03T04:01:35.843-07:00"},{"datasetid": "food-vendors", "recordid": "9def358eb4ed8ace9aeaaae45c42eea549300356", "fields": {"status": "open", "description": "Hot Dogs", "geo_localarea": "Downtown", "geom": {"type": "Point", "coordinates": [-123.122660630478, 49.2830840428154]}, "location": "South Side of 900 Robson St - 12 Metres East of Burrard St", "key": "DT06", "business_name": "Van Dog", "vendor_type": "vendor_food"}, "record_timestamp": "2019-06-03T04:01:35.843-07:00"},{"datasetid": "food-vendors", "recordid": "664c8b9fdd85a51003f7006bcd26cd6784383e9c", "fields": {"status": "open", "description": "Western", "geo_localarea": "Downtown", "geom": {"type": "Point", "coordinates": [-123.118066770004, 49.282314404317]}, "location": "South Side of 600 W Georgia St - 6 Metres East of Granville St", "key": "GM04", "business_name": "Van Dog", "vendor_type": "vendor_food"}, "record_timestamp": "2019-06-03T04:01:35.843-07:00"}]